{
	"789175": {
		"simStates": {
			"ru5y8e": "default",
			"ck29gx": "Sahara_Perspective_simState_001",
			"voypk7": "Sahara_Perspective_simState_002",
			"z23i7k": "Sahara_Perspective_simState_003",
			"47rnla": "Sahara_Perspective_simState_004A",
			"qhpuet": "Sahara_Perspective_simState_004B",
			"sn2rrx": "Sahara_Perspective_simState_004C",
			"kt1y6e": "Sahara_Perspective_simState_005",
			"swovzy": "Sahara_Perspective_simState_006",
			"raw663": "Sahara_Perspective_simState_007",
			"giy1iy": "Sahara_Perspective_simState_007_IMG",
			"us171o": "Sahara_Perspective_simState_008",
			"xdpreu": "Sahara_Perspective_simState_009",
			"1yc1ja": "Sahara_Perspective_simState_010",
			"orumf7": "Sahara_Perspective_simState_011",
			"p582z0": "Sahara_Perspective_simState_012A",
			"s16437": "Sahara_Perspective_simState_012B",
			"f17hpy": "Sahara_Perspective_simState_013",
			"9wq64t": "Sahara_Perspective_simState_014",
			"v1dpud": "Sahara_Perspective_simState_015",
			"c1ifcz": "Sahara_Perspective_simState_022",
			"pwle7w": "Sahara_Perspective_simState_024",
			"y3tf3x": "Sahara_Perspective_simState_025",
			"i9tozw": "Sahara_Perspective_simState_026",
			"ggs6w2": "Sahara_Perspective_simState_029A",
			"1ahxoy": "Sahara_Perspective_simState_029B",
			"lektig": "Sahara_Perspective_simState_029C",
			"h63cxr": "Sahara_Perspective_simState_030",
			"b3m006": "Sahara_Perspective_simState_031",
			"h0z0yp": "Sahara_Perspective_simState_032A",
			"rlsv5f": "Sahara_Perspective_simState_032B",
			"3vn4wd": "Sahara_Perspective_simState_032C",
			"uecxue": "Sahara_Perspective_simState_033",
			"3yv5bs": "Sahara_Perspective_simState_034",
			"k239zh": "Sahara_Perspective_simState_035",
			"c1pnbm": "Sahara_Perspective_simState_036",
			"lf3o4u": "Sahara_Perspective_simState_037",
			"vu6dq3": "Sahara_Perspective_simState_038",
			"t1yrw6": "Sahara_Perspective_simState_039",
			"rti5h8": "Sahara_Perspective_simState_040",
			"sxri3t": "Sahara_Perspective_simState_040_endLoop",
			"51a4u5": "Sahara_Perspective_simState_041",
			"1raam6": "Sahara_Perspective_simState_042",
			"dvpyuw": "Sahara_Perspective_simState_043",
			"7h2miu": "sahara_Perspective_simState_044",
			"r6ww4d": "sahara_Perspective_simState_048",
			"8bo05e": "sahara_Perspective_simState_049",
			"npqm7k": "sahara_Perspective_simState_050",
			"59bzn4": "Sahara_Perspective_simState_051",
			"8u6n73": "Sahara_Perspective_simState_052",
			"oboode": "Sahara_Perspective_simState_053",
			"mfbwdz": "Sahara_Perspective_simState_054",
			"xb5vzo": "Sahara_Perspective_simState_055",
			"o72d3h": "sahara_Perspective_simState_056A",
			"8unplg": "sahara_Perspective_simState_056B",
			"rpmexm": "sahara_Perspective_simState_057",
			"iha2ub": "sahara_Perspective_simState_058",
			"6yvznd": "sahara_Perspective_simState_060",
			"3usurg": "sahara_Perspective_simState_061A",
			"w4dfrk": "sahara_Perspective_simState_061B",
			"dktuif": "sahara_Perspective_simState_061C",
			"ruptro": "sahara_Perspective_simState_062A",
			"moscdt": "sahara_Perspective_simState_062B"
		}
	},
	"789586": {
		"simStates": {
			"2llw7t": "default",
			"0qs1lx": "Sahara_Farm_Map_simState_001",
			"h3xms5": "Sahara_Farm_Map_simState_001b",
			"tv6018": "Sahara_Farm_Map_simState_002",
			"397t1l": "Sahara_Farm_Map_simState_003",
			"4scy6k": "Sahara_Farm_Map_simState_004",
			"6dh6aa": "Sahara_Farm_Map_simState_005",
			"edov9y": "Sahara_Farm_Map_simState_006",
			"kprzmz": "Sahara_Farm_Map_simState_007",
			"5n8bll": "Sahara_Farm_Map_simState_008",
			"bso7wk": "Sahara_Farm_Map_simState_008b",
			"932fjw": "Sahara_Farm_Map_simState_009",
			"or4iyr": "Sahara_Farm_Map_simState_009b",
			"d9yj8a": "Sahara_Farm_Map_simState_010",
			"i7qrgb": "Sahara_Farm_Map_simState_011",
			"6s124l": "Sahara_Farm_Map_simState_012",
			"ln93aq": "Sahara_Farm_Map_simState_013",
			"joc92n": "Sahara_Farm_Map_simState_014",
			"phsquo": "Sahara_Farm_Map_simState_015",
			"j3h5tm": "Sahara_Farm_Map_simState_016",
			"wxt43p": "Sahara_Farm_Map_simState_017",
			"rmpnu5": "Sahara_Farm_Map_simState_018",
			"aypmb5": "Sahara_Farm_Map_simState_019",
			"4nakns": "Sahara_Farm_Map_simState_020",
			"swn4o4": "Sahara_Farm_Map_simState_021",
			"1fisou": "Sahara_Farm_Map_simState_022",
			"hexybk": "Sahara_Farm_Map_simState_023",
			"5bc25a": "Sahara_Farm_Map_simState_024",
			"mif567": "Sahara_Farm_Map_simState_025",
			"17xvxo": "Sahara_Farm_Map_simState_026",
			"tb2e5t": "Sahara_Farm_Map_simState_027",
			"2cftam": "Sahara_Farm_Map_simState_028",
			"3d3n4j": "Sahara_Farm_Map_simState_028b",
			"i0z8kc": "Sahara_Farm_Map_simState_029",
			"2mew0m": "Sahara_Farm_Map_simState_030",
			"8081rp": "Sahara_Farm_Map_simState_031",
			"zhtby0": "Sahara_Farm_Map_simState_032",
			"zmkpoi": "Sahara_Farm_Map_simState_033",
			"rccmvh": "Sahara_Farm_Map_simState_033b",
			"5jbi98": "Sahara_Farm_Map_simState_034",
			"c0w1ud": "Sahara_Farm_Map_simState_034b",
			"xr2v9d": "Sahara_Farm_Map_simState_035",
			"xsf891": "Sahara_Farm_Map_simState_036",
			"8b5j7y": "Sahara_Farm_Map_simState_036b",
			"lkam7a": "Sahara_Farm_Map_simState_037",
			"zgtpjq": "Sahara_Farm_Map_simState_038",
			"vo8p52": "Sahara_Farm_Map_simState_039",
			"qr6dvo": "Sahara_Farm_Map_simState_040",
			"m8cumq": "Sahara_Farm_Map_simState_041",
			"aqrc1f": "Sahara_Farm_Map_simState_042",
			"fduoyb": "Sahara_Farm_Map_simState_042b",
			"abw7jb": "Sahara_Farm_Map_simState_043",
			"0db265": "Sahara_Farm_Map_simState_044",
			"lmiuyk": "Sahara_Farm_Map_simState_044b",
			"vc7ng4": "Sahara_Farm_Map_simState_045",
			"srh15n": "Sahara_Farm_Map_simState_046"
		}
	}
}